sprime/__init__.py
sprime/_version.py
sprime/hill_fitting.py
sprime/reporting.py
sprime/sprime.py
sprime-0.1.0.dist-info/METADATA
sprime-0.1.0.dist-info/WHEEL
sprime-0.1.0.dist-info/licenses/LICENSE
sprime-0.1.0.dist-info/RECORD
