Metadata-Version: 2.4
Name: sprime
Version: 0.1.0
Summary: A biomedical library for screening high-throughput screening data in preclinical drug studies
Project-URL: Homepage, https://github.com/mocomakers/sprime
Project-URL: Documentation, https://github.com/mocomakers/sprime#readme
Project-URL: Repository, https://github.com/mocomakers/sprime
Project-URL: Issues, https://github.com/mocomakers/sprime/issues
Author-email: Matthew Zamora <matt@mocomakers.com>
License: MIT
License-File: LICENSE
Keywords: biomedical,drug-screening,high-throughput-screening,preclinical
Classifier: Development Status :: 3 - Alpha
Classifier: Intended Audience :: Science/Research
Classifier: License :: OSI Approved :: MIT License
Classifier: Programming Language :: Python :: 3
Classifier: Topic :: Scientific/Engineering
Classifier: Topic :: Scientific/Engineering :: Bio-Informatics
Classifier: Topic :: Scientific/Engineering :: Medical Science Apps.
Classifier: Topic :: Software Development :: Libraries :: Python Modules
Requires-Python: >=3.8
Requires-Dist: numpy<3.0,>=1.20.0
Requires-Dist: scipy>=1.7.0
Provides-Extra: dev
Requires-Dist: pdoc3; extra == 'dev'
Requires-Dist: pre-commit; extra == 'dev'
Requires-Dist: pytest-cov>=4.0.0; extra == 'dev'
Requires-Dist: pytest>=7.0.0; extra == 'dev'
